<?xml version="1.0" encoding="UTF-8" standalone="no"?>
<students>

    <student Id="3">
        <serialNumber>sn3</serialNumber>
        <name>name3</name>
        <group>3</group>
    </student>
    <student Id="6">
        <serialNumber>sn6</serialNumber>
        <name>name6</name>
        <group>3</group>
    </student>
    <student Id="9">
        <serialNumber>sn9</serialNumber>
        <name>name9</name>
        <group>3</group>
    </student>
    <student Id="11">
        <serialNumber>sn11</serialNumber>
        <name>name11</name>
        <group>2</group>
    </student>
    <student Id="14">
        <serialNumber>sn14</serialNumber>
        <name>name14</name>
        <group>2</group>
    </student>
    <student Id="17">
        <serialNumber>sn17</serialNumber>
        <name>name17</name>
        <group>2</group>
    </student>
    <student Id="20">
        <serialNumber>sn20</serialNumber>
        <name>name20</name>
        <group>2</group>
    </student>
    <student Id="10">
        <serialNumber>sn10</serialNumber>
        <name>name10</name>
        <group>1</group>
    </student>
    <student Id="13">
        <serialNumber>sn13</serialNumber>
        <name>name13</name>
        <group>1</group>
    </student>
    <student Id="16">
        <serialNumber>sn16</serialNumber>
        <name>name16</name>
        <group>1</group>
    </student>
    <student Id="19">
        <serialNumber>sn19</serialNumber>
        <name>name19</name>
        <group>1</group>
    </student>
    <student Id="1">
        <serialNumber>sn1</serialNumber>
        <name>name1</name>
        <group>1</group>
    </student>

    <student Id="7">
        <serialNumber>sn7</serialNumber>
        <name>name7</name>
        <group>1</group>
    </student>
    <student Id="2">
        <serialNumber>sn2</serialNumber>
        <name>name2</name>
        <group>2</group>
    </student>
    <student Id="5">
        <serialNumber>sn5</serialNumber>
        <name>name5</name>
        <group>2</group>
    </student>
    <student Id="8">
        <serialNumber>sn8</serialNumber>
        <name>name8</name>
        <group>2</group>
    </student>
    <student Id="12">
        <serialNumber>sn12</serialNumber>
        <name>name12</name>
        <group>3</group>
    </student>
    <student Id="15">
        <serialNumber>sn15</serialNumber>
        <name>name15</name>
        <group>3</group>
    </student>
    <student Id="18">
        <serialNumber>sn18</serialNumber>
        <name>name18</name>
        <group>3</group>
    </student>
</students>